kontext/__init__.py
kontext/log_record.py
kontext/main.py
kontext/py.typed
kontext-1.3.0.dist-info/LICENSE
kontext-1.3.0.dist-info/METADATA
kontext-1.3.0.dist-info/WHEEL
kontext-1.3.0.dist-info/RECORD
