Metadata-Version: 2.1
Name: kontext
Version: 1.3.0
Summary: Easy contextual information logging
Home-page: https://pypi.org/project/kontext
License: MIT
Keywords: contextvar,logging,context-logging
Author: Danil Akhtarov
Author-email: daxartio@gmail.com
Requires-Python: >=3.7.1,<4.0.0
Classifier: License :: OSI Approved :: MIT License
Classifier: Programming Language :: Python :: 3
Classifier: Programming Language :: Python :: 3.8
Classifier: Programming Language :: Python :: 3.9
Classifier: Programming Language :: Python :: 3.10
Classifier: Programming Language :: Python :: 3.11
Classifier: Programming Language :: Python :: 3.12
Requires-Dist: typing-extensions (>=4.5.0,<5.0.0)
Project-URL: Changelog, https://github.com/daxartio/kontext/blob/main/CHANGELOG.md
Project-URL: Repository, https://github.com/daxartio/kontext
